bashdoctest/__init__.py
bashdoctest/_version.py
bashdoctest/core.py
bashdoctest/validators.py
bashdoctest-0.1.2.dist-info/LICENSE
bashdoctest-0.1.2.dist-info/METADATA
bashdoctest-0.1.2.dist-info/WHEEL
bashdoctest-0.1.2.dist-info/top_level.txt
bashdoctest-0.1.2.dist-info/RECORD
