Metadata-Version: 2.1
Name: bashdoctest
Version: 0.1.2
Summary: "A Doctest-type Command Line Application Tester"
Home-page: https://github.com/juledwar/bashdoctest
Author: "Michael Delgado, Julian Edwards"
Maintainer: Julian Edwards
Maintainer-email: juledwar@cisco.com
License: "MIT license"
Keywords: bashdoctest
Classifier: Development Status :: 4 - Beta
Classifier: Intended Audience :: Developers
Classifier: License :: OSI Approved :: MIT License
Classifier: Natural Language :: English
Classifier: Programming Language :: Python :: 3
Classifier: Programming Language :: Python :: 3.3
Classifier: Programming Language :: Python :: 3.4
Classifier: Programming Language :: Python :: 3.5
Classifier: Programming Language :: Python :: 3.6
Classifier: Environment :: Console
Classifier: Intended Audience :: Developers
Classifier: Intended Audience :: Information Technology
Classifier: Intended Audience :: System Administrators
Classifier: Natural Language :: English
Classifier: Topic :: Utilities
License-File: LICENSE
Requires-Dist: click (>=6.0)
Provides-Extra: test
Requires-Dist: click (>=6.0) ; extra == 'test'
Requires-Dist: Sphinx (>=1.4.1) ; extra == 'test'
Requires-Dist: sphinx-rtd-theme (>=0.1.0) ; extra == 'test'
Requires-Dist: jinja2 (>=2.8) ; extra == 'test'
Requires-Dist: pip (>=8.0) ; extra == 'test'
Requires-Dist: wheel (>=0.27) ; extra == 'test'
Requires-Dist: flake8 (>=2.0) ; extra == 'test'
Requires-Dist: tox (>=2.3.0) ; extra == 'test'
Requires-Dist: coverage (>=4.0) ; extra == 'test'
Requires-Dist: pytest (>=3.0) ; extra == 'test'
Requires-Dist: pytest-cov (>=2.0) ; extra == 'test'
Requires-Dist: pytest-runner (>=2.5) ; extra == 'test'
Requires-Dist: build (>=0.7.0) ; extra == 'test'
Requires-Dist: twine (>=3.4.2) ; extra == 'test'
